[
    {
        "actionName": "vuser_init",
        "steps": [
            {
                "stepId": "STEP1",
                "stepName": "Url: WebTours",
                "infFile": "t1.inf",
                "time": 1575124643207
            },
            {
                "stepId": "STEP2",
                "stepName": "Submit Data: login.pl",
                "infFile": "t2.inf",
                "time": 1575124643511
            }
        ],
        "transactions": [
            {
                "transactionName": "UC01_TR01_Login",
                "rawStartTime": 1575124643213,
                "rawEndTime": 1575124643511,
                "thinkTime": 0.0,
                "wastedTime": 0.009755373001098633
            }
        ]
    }
]