{"OutputFileHashSum":"FE02EFC8147AF8738FA16AD2D948A860EA1BBDD00691C9CC98486B3DD710A79A","Converted":true,"OutputModifyDate":"2019-11-30T16:02:34.2381782Z","Metadatas":[],"MetadataTypes":[{"CategoryName":"VuGen.Replay","MetadataTypeName":"HP.LR.Vugen.NotifySavingParameter","Id":1},{"CategoryName":"VuGen.Replay","MetadataTypeName":"HP.LR.Vugen.NotifyTransaction","Id":2},{"CategoryName":"VuGen.Replay","MetadataTypeName":"HP.LR.Vugen.NotifyAny","Id":3},{"CategoryName":"VuGen.Replay","MetadataTypeName":"HP.LR.Vugen.Iteration","Id":4}]}